{
  "device_id": "tmp105",
  "attachment_type": "i2c_sensor",
  "required_bus_type": "i2c",
  "address_mode": "7-bit",
  "addressing": {
    "default": "0x48",
    "alternates": [
      "0x49",
      "0x4A",
      "0x4B"
    ],
    "selection_rule": "A0/A1 select one of the documented TMP105 addresses."
  },
  "required_attachment": {
    "signals": [],
    "notes": [
      "Minimal driver reads the temperature register directly in polling mode."
    ]
  },
  "optional_attachment": {
    "alert_pin": "optional",
    "address_select_pins": [
      "A0",
      "A1"
    ]
  },
  "default_overrides": {
    "bus_instance": null,
    "irq": "absent",
    "dma": "absent",
    "reset_gpio": null,
    "power_gpio": null
  },
  "notes": [
    "Reference drivers use the default 12-bit temperature format and do not configure thermostat outputs."
  ],
  "evidence": [
    "DriverGen/data/raw/tmp105",
    "DriverGen/data/references/tmp105/*/*_ref.h"
  ]
}