{
  "binding_id": "chibios_generic_hal_gpio_timing_default",
  "platform_id": "chibios_generic_hal",
  "connection_type": "gpio_timing",
  "mode": "polling",
  "bus_instance": "default_gpio_slot",
  "bus_instance_kind": "pal_line",
  "bus_symbol": "PAL_LINE(GPIOA, 0)",
  "backend": "ChibiOS PAL GPIO",
  "address_mode": null,
  "fixed_attachment": {
    "trig_line": "PAL_LINE(GPIOA, 0)",
    "echo_line": "PAL_LINE(GPIOA, 1)"
  },
  "notes": [
    "Default ChibiOS GPIO timing binding uses PAL line macros."
  ],
  "evidence": [
    "DriverGen/data/rtos/chibios/os/hal/include/hal_pal.h"
  ]
}
